{
  "modelo_001": {
    "id": "modelo_001",
    "filename": "modelo_001_rf_📋_entrenamiento_mpg_20260524_132613.pkl",
    "model_key": "rf",
    "dataset_name": "📋 entrenamiento_mpg",
    "problem_type": "regression",
    "created_at": "2026-05-24T13:26:13.947460",
    "file_size_mb": 1.98,
    "target_col": "mpg",
    "num_features": 1,
    "cat_features": 0,
    "metrics": {
      "r2_score": 0.999153994426406,
      "rmse": 0.33066737452626044,
      "mae": 0.1692798113749998
    },
    "train_params": {
      "source": "api",
      "model_key": "rf",
      "problem_type": "regression",
      "test_size": 0.2,
      "cv_folds": 5,
      "n_bootstraps": 3
    },
    "target_classes": null
  },
  "modelo_002": {
    "id": "modelo_002",
    "filename": "modelo_002_rf_📋_entre_temo_c_f_20260524_172627.pkl",
    "model_key": "rf",
    "dataset_name": "📋 entre_temo_c_f",
    "problem_type": "regression",
    "created_at": "2026-05-24T17:26:27.934719",
    "file_size_mb": 1.88,
    "target_col": "temp_f",
    "num_features": 1,
    "cat_features": 0,
    "metrics": {
      "r2_score": 0.99973664082652,
      "rmse": 0.38448383411923576,
      "mae": 0.2997931436475126
    },
    "train_params": {
      "source": "api",
      "model_key": "rf",
      "problem_type": "regression",
      "test_size": 0.2,
      "cv_folds": 5,
      "n_bootstraps": 3
    },
    "target_classes": null
  },
  "modelo_003": {
    "id": "modelo_003",
    "filename": "modelo_003_xgb_📋_entre_temo_c_f_20260524_172709.pkl",
    "model_key": "xgb",
    "dataset_name": "📋 entre_temo_c_f",
    "problem_type": "regression",
    "created_at": "2026-05-24T17:27:08.802032",
    "file_size_mb": 0.47,
    "target_col": "temp_f",
    "num_features": 1,
    "cat_features": 0,
    "metrics": {
      "r2_score": 0.9990298616689488,
      "rmse": 0.7379393871025693,
      "mae": 0.6224933396357422
    },
    "train_params": {
      "source": "api",
      "model_key": "xgb",
      "problem_type": "regression",
      "test_size": 0.2,
      "cv_folds": 5,
      "n_bootstraps": 3
    },
    "target_classes": null
  },
  "modelo_004": {
    "id": "modelo_004",
    "filename": "modelo_004_xgb_📋_entrenamiento_financiero_20260524_180525.pkl",
    "model_key": "xgb",
    "dataset_name": "📋 entrenamiento_financiero",
    "problem_type": "binary",
    "created_at": "2026-05-24T18:05:25.911430",
    "file_size_mb": 0.05,
    "target_col": "aprobado",
    "num_features": 9,
    "cat_features": 0,
    "metrics": {},
    "train_params": {
      "source": "api",
      "model_key": "xgb",
      "problem_type": "binary",
      "test_size": 0.2,
      "cv_folds": 5,
      "n_bootstraps": 3
    },
    "target_classes": [
      0,
      1
    ]
  },
  "modelo_005": {
    "id": "modelo_005",
    "filename": "modelo_005_rf_📋_entrenamiento_financiero_20260524_180852.pkl",
    "model_key": "rf",
    "dataset_name": "📋 entrenamiento_financiero",
    "problem_type": "binary",
    "created_at": "2026-05-24T18:08:52.619883",
    "file_size_mb": 0.05,
    "target_col": "aprobado",
    "num_features": 9,
    "cat_features": 0,
    "metrics": {},
    "train_params": {
      "source": "api",
      "model_key": "rf",
      "problem_type": "binary",
      "test_size": 0.2,
      "cv_folds": 5,
      "n_bootstraps": 3
    },
    "target_classes": [
      0,
      1
    ]
  },
  "modelo_006": {
    "id": "modelo_006",
    "filename": "modelo_006_xgb_📋_entrenamiento_financiero_20260524_182418.pkl",
    "model_key": "xgb",
    "dataset_name": "📋 entrenamiento_financiero",
    "problem_type": "regression",
    "created_at": "2026-05-24T18:24:18.574347",
    "file_size_mb": 0.33,
    "target_col": "score_credito",
    "num_features": 9,
    "cat_features": 0,
    "metrics": {
      "r2_score": 0.9684353230509644,
      "rmse": 10.87242912941439,
      "mae": 6.32845458984375
    },
    "train_params": {
      "source": "api",
      "model_key": "xgb",
      "problem_type": "regression",
      "test_size": 0.2,
      "cv_folds": 5,
      "n_bootstraps": 3
    },
    "target_classes": null
  },
  "modelo_007": {
    "id": "modelo_007",
    "filename": "modelo_007_xgb_📋_entrenamiento_financiero_20260524_191846.pkl",
    "model_key": "xgb",
    "dataset_name": "📋 entrenamiento_financiero",
    "problem_type": "regression",
    "created_at": "2026-05-24T19:18:46.217782",
    "file_size_mb": 0.33,
    "target_col": "score_credito",
    "num_features": 9,
    "cat_features": 0,
    "metrics": {
      "r2_score": 0.9684353230509644,
      "rmse": 10.87242912941439,
      "mae": 6.32845458984375
    },
    "train_params": {
      "source": "api",
      "model_key": "xgb",
      "problem_type": "regression",
      "test_size": 0.2,
      "cv_folds": 5,
      "n_bootstraps": 3
    },
    "target_classes": null
  },
  "modelo_008": {
    "id": "modelo_008",
    "filename": "modelo_008_xgb_📋_entrenamiento_financiero_20260524_215545.pkl",
    "model_key": "xgb",
    "dataset_name": "📋 entrenamiento_financiero",
    "problem_type": "binary",
    "created_at": "2026-05-24T21:55:45.657618",
    "file_size_mb": 0.05,
    "target_col": "aprobado",
    "num_features": [
      "id_cliente",
      "edad",
      "ingreso_mensual",
      "monto_solicitado",
      "plazo_meses",
      "tasa_interes",
      "historial_credito",
      "deuda_actual",
      "score_credito"
    ],
    "cat_features": [],
    "metrics": {},
    "train_params": {
      "source": "api",
      "model_key": "xgb",
      "problem_type": "binary",
      "test_size": 0.2,
      "cv_folds": 5,
      "n_bootstraps": 3
    },
    "target_classes": [
      0,
      1
    ],
    "meta": {
      "problem_type": "binary",
      "num_features": [
        "id_cliente",
        "edad",
        "ingreso_mensual",
        "monto_solicitado",
        "plazo_meses",
        "tasa_interes",
        "historial_credito",
        "deuda_actual",
        "score_credito"
      ],
      "cat_features": [],
      "label_encoder": null,
      "target_classes": [
        0,
        1
      ],
      "target_col": "aprobado",
      "n_features_in": 9,
      "feature_baselines": {
        "id_cliente": 25.5,
        "edad": 38.0,
        "ingreso_mensual": 5650.0,
        "monto_solicitado": 31500.0,
        "plazo_meses": 36.0,
        "tasa_interes": 14.35,
        "historial_credito": 712.5,
        "deuda_actual": 2150.0,
        "score_credito": 712.5
      }
    }
  }
}